CHANGES.rst
LICENSE.txt
MANIFEST.in
README.rst
setup.py
src/bst/__init__.py
src/bst.pygasus.wsgi.egg-info/PKG-INFO
src/bst.pygasus.wsgi.egg-info/SOURCES.txt
src/bst.pygasus.wsgi.egg-info/dependency_links.txt
src/bst.pygasus.wsgi.egg-info/entry_points.txt
src/bst.pygasus.wsgi.egg-info/namespace_packages.txt
src/bst.pygasus.wsgi.egg-info/not-zip-safe
src/bst.pygasus.wsgi.egg-info/requires.txt
src/bst.pygasus.wsgi.egg-info/top_level.txt
src/bst/pygasus/__init__.py
src/bst/pygasus/wsgi/__init__.py
src/bst/pygasus/wsgi/configure.zcml
src/bst/pygasus/wsgi/errorhandling.py
src/bst/pygasus/wsgi/events.py
src/bst/pygasus/wsgi/http.py
src/bst/pygasus/wsgi/interfaces.py
src/bst/pygasus/wsgi/publisher.py
src/bst/pygasus/wsgi/server.py